Metadata-Version: 2.1
Name: jsonmix
Version: 0.1.0
Summary: A library for validate json
Home-page: https://github.com/Suspir0n/jsonmix.git
Author: Evandro Silva
Author-email: evandrojunior1615@gmail.com
Maintainer: ['Evandro Silva', 'Ismael Carvalho']
Maintainer-email: evandrojunior1615@gmail.com
License: MIT
Download-URL: https://github.com/Suspir0n/jsonmix/archive/refs/tags/0.1.0.tar.gz
Platform: UNKNOWN
Requires-Python: >=3.6
License-File: LICENSE.txt
